lambda_zip/__init__.py
lambda_zip/aws_lambda_function.py
lambda_zip/aws_lambda_layer.py
lambda_zip/aws_lambda_layer_version.py
lambda_zip-1.23060401.dist-info/LICENSE
lambda_zip-1.23060401.dist-info/METADATA
lambda_zip-1.23060401.dist-info/WHEEL
lambda_zip-1.23060401.dist-info/entry_points.txt
lambda_zip-1.23060401.dist-info/top_level.txt
lambda_zip-1.23060401.dist-info/RECORD
